CHANGES.txt
LICENSE.txt
MANIFEST.in
setup.cfg
setup.py
autolink_py/__init__.py
autolink_py.egg-info/PKG-INFO
autolink_py.egg-info/SOURCES.txt
autolink_py.egg-info/dependency_links.txt
autolink_py.egg-info/top_level.txt
autolink_py/component/__init__.py
autolink_py/component/mail.py
autolink_py/component/url.py
autolink_py/core/__init__.py
autolink_py/core/auto_linker.py
autolink_py/utils/__init__.py
autolink_py/utils/helper.py
autolink_py/values/__init__.py
autolink_py/values/replace_type.py