Metadata-Version: 1.0
Name: autolink-py
Version: 0.2.1
Summary: UNKNOWN
Home-page: https://github.com/joanne-tseng/autolink_py
Author: Tzeng
Author-email: tseng0211@gmail.com
License: UNKNOWN
Platform: UNKNOWN
